AUTHORS
LICENSE
MANIFEST.in
README.md
setup.py
bozor/__about__.py
bozor/__init__.py
bozor/decorators.py
bozor/exceptions.py
bozor.egg-info/PKG-INFO
bozor.egg-info/SOURCES.txt
bozor.egg-info/dependency_links.txt
bozor.egg-info/not-zip-safe
bozor.egg-info/requires.txt
bozor.egg-info/top_level.txt
bozor/aws/__init__.py
bozor/aws/arn.py
bozor/aws/iam/__init__.py
bozor/aws/iam/role.py
bozor/aws/iam/user.py
bozor/tests/__init__.py