Metadata-Version: 1.0
Name: bozor
Version: 0.0.1dev2
Summary: A higher level package to retrieve details on AWS items.
Home-page: https://github.com/monkeysecurity/bozor
Author: Patrick Kelley
Author-email: patrick@netflix.com
License: UNKNOWN
Platform: UNKNOWN
